LICENSE
MANIFEST.in
README.md
setup.py
evercam/__init__.py
evercam/errors.py
evercam/evercam.py
evercam/test_evercam.py
evercam.egg-info/PKG-INFO
evercam.egg-info/SOURCES.txt
evercam.egg-info/dependency_links.txt
evercam.egg-info/requires.txt
evercam.egg-info/top_level.txt