Metadata-Version: 1.1
Name: evercam
Version: 0.1.3
Summary: UNKNOWN
Home-page: http://www.evercam.io/
Author: Evercam
Author-email: tomasz.jama@mhlabs.net
License: Copyright (C) 2013 Evercam (http://www.evercam.io)
